changelogtxt_parser/__init__.py
changelogtxt_parser/_cli.py
changelogtxt_parser/_utils.py
changelogtxt_parser/app.py
changelogtxt_parser/serdes.py
changelogtxt_parser/version.py
changelogtxt_parser-1.0.0rc2.dist-info/licenses/LICENSE
changelogtxt_parser-1.0.0rc2.dist-info/METADATA
changelogtxt_parser-1.0.0rc2.dist-info/WHEEL
changelogtxt_parser-1.0.0rc2.dist-info/entry_points.txt
changelogtxt_parser-1.0.0rc2.dist-info/top_level.txt
changelogtxt_parser-1.0.0rc2.dist-info/RECORD
