Metadata-Version: 2.4
Name: changelogtxt-parser
Version: 1.0.0rc2
Summary: Parses changelog txt files
Author-email: David Angarita <davidangarita.sistemas@gmail.com>
Maintainer-email: Andrew Pikul <ajpikul@gmail.com>
License: MIT License
Project-URL: Homepage, https://github.com/geopozo/changelogtxt-parser
Project-URL: Repository, https://github.com/geopozo/changelogtxt-parser
Requires-Python: >=3.10
License-File: LICENSE
Requires-Dist: logistro>=1.1.0
Requires-Dist: packaging>=25.0
Requires-Dist: semver>=3.0.4
Dynamic: license-file
